fields-5.0.0.dist-info/DESCRIPTION.rst
fields-5.0.0.dist-info/METADATA
fields-5.0.0.dist-info/top_level.txt
fields-5.0.0.dist-info/RECORD
fields-5.0.0.dist-info/WHEEL
fields-5.0.0.dist-info/metadata.json
fields/extras.py
fields/py2ordereddict.py
fields/__init__.py
